[
    {
        "name": "Subhiksha S",
        "email": "1nt24cs296.subhiksha@nmit.ac.in"
    },
    {
        "name": "Priya Darshini P",
        "email": "ppriyadarshini363@gmail.com"
    },
    {
        "name": "Gunjan Siddharth",
        "email": "gunjansiddharth03@gmail.com"
    },
    {
        "name": "Suhascp",
        "email": "cpsuhas07@gmail.com"
    },
    {
        "name": "Aditya Kumar",
        "email": "adityakumarscpa@gmail.com"
    },
    {
        "name": "LOKANATHAN MONIKA",
        "email": "monikalokanathan89@gmail.com"
    },
    {
        "name": "Monisha",
        "email": "monishasathram2006@gmail.com"
    },
    {
        "name": "SHIVA M",
        "email": "shivarocks2006@gmail.com"
    },
    {
        "name": "R R Sushmitha Raksha",
        "email": "srksha92795@gmail.com"
    },
    {
        "name": "Kushal.R",
        "email": "sahanakushal2613@gmail.com"
    },
    {
        "name": "Shashank C",
        "email": "shashankchandrapaa@gmail.com"
    },
    {
        "name": "Chithra",
        "email": "nrchithra2006@gmail.com"
    },
    {
        "name": "Ramya G N",
        "email": "ramyaramyagn306@gmail.com"
    },
    {
        "name": "Moulya M Patel",
        "email": "moulya213@gmail.com"
    },
    {
        "name": "Subharup Nandi",
        "email": "subharupn@gmail.com"
    },
    {
        "name": "Sandeep",
        "email": "s62588874@gmail.com"
    },
    {
        "name": "Sidharth",
        "email": "sidharthsathish06@gmail.com"
    },
    {
        "name": "Varshanth",
        "email": "bvarshanth1@gmail.com"
    },
    {
        "name": "Mohammed Issaqh",
        "email": "mdissaqh2007@gmail.com"
    },
    {
        "name": "Srija Mondal",
        "email": "srija.mondal.j2006@gmail.com"
    },
    {
        "name": "Rahul",
        "email": "rdasrd54321@gmail.com"
    },
    {
        "name": "Satyam Mishra",
        "email": "mishrashtyam@gmail.com"
    },
    {
        "name": "Astha Sharma",
        "email": "astha40713@gmail.com"
    },
    {
        "name": "Sneha Mishra",
        "email": "jainlavanya867@gmail.com"
    },
    {
        "name": "Meghana Mallarapu",
        "email": "meghanambng@gmail.com"
    },
    {
        "name": "Arya L S",
        "email": "arayals.u01cj22s0027@gmail.com"
    },
    {
        "name": "Rohit singh",
        "email": "sr6901627@gmail.com"
    },
    {
        "name": "Anusha Mehar",
        "email": "anushamehar7678@gmail.com"
    },
    {
        "name": "Shubham Mehta",
        "email": "shubhmehta2604@gmail.com"
    },
    {
        "name": "Avikumar Chovatiya",
        "email": "avichovatiya0@gmail.com"
    },
    {
        "name": "Ushakirana S",
        "email": "ushakiranas26@gmail.com"
    },
    {
        "name": "satyam kumar",
        "email": "satyamkumar9250@gmail.com"
    },
    {
        "name": "Sukhdeep Singh",
        "email": "sukhjk2006@gmail.com"
    },
    {
        "name": "Aspaan Kaur",
        "email": "aspaan.kaur@gmail.com"
    },
    {
        "name": "Battina Roy",
        "email": "battinaroyrg2006@gmail.com"
    },
    {
        "name": "Rahul MR",
        "email": "rahulrajvishnu4@gmail.com"
    },
    {
        "name": "Abhi Dudharejiya",
        "email": "dudharejiya1212@gmail.com"
    },
    {
        "name": "Prathiksha hombegowdana Doddi Nagaraju",
        "email": "prathikshahn07@gmail.com"
    },
    {
        "name": "Sagar Singh",
        "email": "sagarsingh.webdev@gmail.com"
    },
    {
        "name": "Dhruva B",
        "email": "dhruvab479@gmail.com"
    },
    {
        "name": "Dhiraj G",
        "email": "dhirajg.5106@gmail.com"
    },
    {
        "name": "Durgesh Mani Tiwari",
        "email": "durgeshmanitiwari2005@gmail.com"
    },
    {
        "name": "Priya C.S",
        "email": "priyasgowda1626@gmail.com"
    },
    {
        "name": "Pruthvi P",
        "email": "ppruthvi460@gmail.com"
    },
    {
        "name": "Arpita Bhat",
        "email": "bhatarpita16@gmail.com"
    },
    {
        "name": "Arunima Parya",
        "email": "paryaarunima96@gmail.com"
    },
    {
        "name": "Nishu Kumari",
        "email": "nishukarn788@gmail.com"
    },
    {
        "name": "Astha Tiwari",
        "email": "tiwariastha1204@gmail.com"
    },
    {
        "name": "PREM YADAV",
        "email": "premyadav27622@gmail.com"
    },
    {
        "name": "Abhinav Kumar",
        "email": "abhikumar180206@gmail.com"
    },
    {
        "name": "ADARSH SHUKLA",
        "email": "aadarshshukla2025@gmail.com"
    },
    {
        "name": "Aditya Shukla",
        "email": "adityashukla21012006@gmail.com"
    },
    {
        "name": "Sachin K",
        "email": "sachinzn28@gmail.com"
    },
    {
        "name": "Arya Ranjan",
        "email": "aryan.inlook@gmail.com"
    },
    {
        "name": "Kolusu Naga Sai Manikanta",
        "email": "nagasaiyadav2002@gmail.com"
    },
    {
        "name": "Smruthi K R",
        "email": "smruthi.kr2003@gmail.com"
    },
    {
        "name": "Mahesh L S",
        "email": "maheshls967@gmail.com"
    },
    {
        "name": "Balaji B",
        "email": "b7232870@gmail.com"
    },
    {
        "name": "Dhanush Kumar NS",
        "email": "dhanushkumarns67@gmail.com"
    },
    {
        "name": "Dhanush K S",
        "email": "dhanushdeeksha6@gmail.com"
    },
    {
        "name": "Aryan Parashar",
        "email": "parashararyan45@gmail.com"
    },
    {
        "name": "Jashwanth",
        "email": "jashwanthlokande233@gmail.com"
    },
    {
        "name": "Dhruv Oberoi",
        "email": "oberoidhruv6@gmail.com"
    },
    {
        "name": "Mansi Sondhi",
        "email": "mansisondhi103@gmail.com"
    },
    {
        "name": "Ashutosh Jha",
        "email": "ashutoshj887@gmail.com"
    },
    {
        "name": "Deepak Gowda",
        "email": "deepugowda.0331@gmail.com"
    },
    {
        "name": "Darshan k h",
        "email": "darshanhalesh6@gmail.com"
    },
    {
        "name": "Mazhar abbas",
        "email": "mazharabbas10010@gmail.com"
    },
    {
        "name": "Chiranthana U",
        "email": "chiranthana153@gmail.com"
    },
    {
        "name": "Yeshwanth",
        "email": "yeshwanthkg@gmail.com"
    },
    {
        "name": "Isha Surana",
        "email": "ishasurana191@gmail.com"
    },
    {
        "name": "Jai Aaditya Prabhu E",
        "email": "jaiaadityaprabhu@gmail.com"
    },
    {
        "name": "S Yeshwini",
        "email": "yeshwini22@gmail.com"
    },
    {
        "name": "Akash Krishna R",
        "email": "akashkrishna7890@gmail.com"
    },
    {
        "name": "Saravana",
        "email": "itzsaravana07@gmail.com"
    },
    {
        "name": "Akshay Kachhadiya",
        "email": "akshaykachhadiya321@gmail.com"
    },
    {
        "name": "Priyanjul Sonkar",
        "email": "priyanjulsonkar@gmail.com"
    },
    {
        "name": "Rajdeep Singh",
        "email": "rajdeep2006ss@gmail.com"
    },
    {
        "name": "Rakshitha M",
        "email": "rakshitha28042006@gmail.com"
    },
    {
        "name": "Rashi Singh",
        "email": "rashi1912singh@gmail.com"
    },
    {
        "name": "AYUSH ROY",
        "email": "ayushhroy.7@gmail.com"
    },
    {
        "name": "Saurabh Pati Tripathi",
        "email": "tripathisaurabh9211@gmail.com"
    },
    {
        "name": "Koushik PR",
        "email": "prkoushik222005@gmail.com"
    },
    {
        "name": "Kritika Taank",
        "email": "taank.kritika@gmail.com"
    },
    {
        "name": "Sandipan Mandal",
        "email": "msandipan0208@gmail.com"
    },
    {
        "name": "Sandeep Chakravartty",
        "email": "sandeepchakravartty@gmail.com"
    },
    {
        "name": "Sri Harsha Thota",
        "email": "sriharsha.dev02@gmail.com"
    },
    {
        "name": "Kirtan Kanetiya",
        "email": "kirtan9207@gmail.com"
    },
    {
        "name": "Prince",
        "email": "princepatel97120@gmail.com"
    },
    {
        "name": "YARUL JAIN",
        "email": "yarul.j@tataelxsi.co.in"
    },
    {
        "name": "Yashkumar U Kolekar",
        "email": "yash.uk060905@gmail.com"
    },
    {
        "name": "Lathika Ekambaram",
        "email": "lathikaekambaram@gmail.com"
    },
    {
        "name": "Vanshika Agarwal",
        "email": "vanshikaagarwal0904@gmail.com"
    },
    {
        "name": "k sudhakar",
        "email": "kunisettisudhakar114@gmail.com"
    },
    {
        "name": "Amogh Kotha Nagaraj",
        "email": "amoghnkotha2023@gmail.com"
    },
    {
        "name": "SHREYANSH SINGH",
        "email": "sshreyansh962@gmail.com"
    },
    {
        "name": "Pritam Pankaj",
        "email": "pritampankaj2941@gmail.com"
    },
    {
        "name": "Poojitha G",
        "email": "poojithag102@gmail.com"
    },
    {
        "name": "Sai Rohan",
        "email": "palusasairohan@gmail.com"
    },
    {
        "name": "Siddanth  Nair",
        "email": "nair.siddanth9027@gmail.com"
    },
    {
        "name": "Anish Bandapelly",
        "email": "bandapellyanish@gmail.com"
    },
    {
        "name": "Divya Raikar",
        "email": "raikardivya15@gmail.com"
    },
    {
        "name": "Praharsh Katyan",
        "email": "katyanpraharsh@gmail.com"
    },
    {
        "name": "Shreyas",
        "email": "rshreyas896@gmail.com"
    },
    {
        "name": "Heramb Mishra",
        "email": "herambmishra181@gmail.com"
    },
    {
        "name": "Malyadri",
        "email": "marnenigalaxy@gmail.com"
    },
    {
        "name": "Jayanth Sahasranamamula",
        "email": "jayanth.sahas@gmail.com"
    },
    {
        "name": "Aditya Tiadi",
        "email": "tiadiaditya@gmail.com"
    },
    {
        "name": "Kushal S",
        "email": "skushal.mys@gmail.com"
    },
    {
        "name": "Muhammad Danish J",
        "email": "m.daanish.aj@gmail.com"
    },
    {
        "name": "Shravani",
        "email": "shravanikalmali@gmail.com"
    },
    {
        "name": "Nithesh V",
        "email": "nithesh.achu27@gmail.com"
    },
    {
        "name": "Prince Kumar",
        "email": "prince07pk12@gmail.com"
    },
    {
        "name": "Vivek Kashyap",
        "email": "vivekkashyap0712@gmail.com"
    },
    {
        "name": "Jyesht M",
        "email": "jyesht147@gmail.com"
    },
    {
        "name": "Tarun Kumar Pathak",
        "email": "tarunkumarpathak999@gmail.com"
    },
    {
        "name": "Nived Shaji",
        "email": "nivedshaji2006@gmail.com"
    },
    {
        "name": "Ajay Kumawat",
        "email": "ajaykumawat01@gmail.com"
    },
    {
        "name": "Karthik M",
        "email": "karm131005@gmail.com"
    },
    {
        "name": "Kush Anchalia",
        "email": "kushanchalia@gmail.com"
    },
    {
        "name": "Kruthika K",
        "email": "kruthikakalmali@gmail.com"
    },
    {
        "name": "Rithvik Krishna D K",
        "email": "rithvikkrishnadk@gmail.com"
    },
    {
        "name": "Anuraag Nandi",
        "email": "nandianuraag@gmail.com"
    },
    {
        "name": "SRIRANJINI KS",
        "email": "sriranjiniks583104@gmail.com"
    },
    {
        "name": "Arkadip Basu",
        "email": "arkadipbasu10@gmail.com"
    },
    {
        "name": "Prashanth Tiwari",
        "email": "tiwariprashanth.2905@gmail.com"
    },
    {
        "name": "Janvi Sheth",
        "email": "janvisheth.1507@gmail.com"
    },
    {
        "name": "Repana Reddy Sekhar",
        "email": "repana.reddysekhar.26@gmail.com"
    },
    {
        "name": "MD TOUFIQUE",
        "email": "ahmedtoufiqkhan37@gmail.com"
    },
    {
        "name": "Harshavardhan Reddy",
        "email": "harsha19821983@gmail.com"
    },
    {
        "name": "Hema",
        "email": "hemapriya9019@gmail.com"
    },
    {
        "name": "Amey Muke",
        "email": "ameymuke252003@gmail.com"
    },
    {
        "name": "Muhammed Ameen",
        "email": "ameens.in19@gmail.com"
    },
    {
        "name": "Ajmal MA",
        "email": "ajmal@quantumx.foundation"
    }
]